h_annot/__init__.py
h_annot/annotation.py
h_annot/api.py
h_annot/exceptions.py
h_annot/oauth.py
python_hypothesis-0.4.2.dist-info/COPYING
python_hypothesis-0.4.2.dist-info/METADATA
python_hypothesis-0.4.2.dist-info/WHEEL
python_hypothesis-0.4.2.dist-info/top_level.txt
python_hypothesis-0.4.2.dist-info/RECORD
