Metadata-Version: 2.1
Name: python-hypothesis
Version: 0.4.2
Summary: Python library for the Hypothes.is API
Home-page: https://github.com/chaselgrove/python-hypothesis
Author: Christian Haselgrove
Author-email: christian.haselgrove@umassmed.edu
License: BSD license
Platform: UNKNOWN
Classifier: Development Status :: 3 - Alpha
Classifier: Environment :: Web Environment
Classifier: Intended Audience :: Developers
Classifier: License :: OSI Approved :: BSD License
Classifier: Natural Language :: English
Classifier: Operating System :: OS Independent
Classifier: Programming Language :: Python
Classifier: Topic :: Internet :: WWW/HTTP
Classifier: Topic :: Software Development :: Libraries
Requires-Dist: requests
Requires-Dist: python-dateutil
Requires-Dist: six
